{
  "balance": 160.01,
  "s1_balance": 127.86,
  "s2_balance": 32.15,
  "s3_balance": 0.0,
  "starting_balance": 500.0,
  "positions": {
    "1566194": {
      "strategy": "S2_lottery",
      "question": "Will the highest temperature in New York City be between 54-55\u00b0F on March 14?",
      "outcome": "Yes",
      "entry_price": 0.0345,
      "shares": 151.89,
      "cost": 5.24,
      "city": "new-york-city",
      "date_str": "2026-03-14",
      "forecast_temp": 51,
      "low": 54,
      "high": 55,
      "opened_at": "2026-03-13T14:00:24.926700"
    },
    "1566195": {
      "strategy": "S2_lottery",
      "question": "Will the highest temperature in New York City be between 56-57\u00b0F on March 14?",
      "outcome": "Yes",
      "entry_price": 0.018,
      "shares": 170.32,
      "cost": 3.07,
      "city": "new-york-city",
      "date_str": "2026-03-14",
      "forecast_temp": 51,
      "low": 56,
      "high": 57,
      "opened_at": "2026-03-13T14:00:24.926735"
    },
    "1566231": {
      "strategy": "S2_lottery",
      "question": "Will the highest temperature in Chicago be between 44-45\u00b0F on March 14?",
      "outcome": "Yes",
      "entry_price": 0.0315,
      "shares": 156.57,
      "cost": 4.93,
      "city": "chicago",
      "date_str": "2026-03-14",
      "forecast_temp": 41,
      "low": 44,
      "high": 45,
      "opened_at": "2026-03-13T14:00:30.540466"
    },
    "1566232": {
      "strategy": "S2_lottery",
      "question": "Will the highest temperature in Chicago be 46\u00b0F or higher on March 14?",
      "outcome": "Yes",
      "entry_price": 0.0055,
      "shares": 1045.97,
      "cost": 5.75,
      "city": "chicago",
      "date_str": "2026-03-14",
      "forecast_temp": 41,
      "low": 46,
      "high": 999,
      "opened_at": "2026-03-13T14:00:30.540498"
    },
    "1566215": {
      "strategy": "S2_lottery",
      "question": "Will the highest temperature in Miami be 75\u00b0F or below on March 14?",
      "outcome": "Yes",
      "entry_price": 0.007,
      "shares": 451.99,
      "cost": 3.16,
      "city": "miami",
      "date_str": "2026-03-14",
      "forecast_temp": 81,
      "low": -999,
      "high": 75,
      "opened_at": "2026-03-13T14:00:34.766868"
    },
    "1566216": {
      "strategy": "S2_lottery",
      "question": "Will the highest temperature in Miami be between 76-77\u00b0F on March 14?",
      "outcome": "Yes",
      "entry_price": 0.0125,
      "shares": 307.54,
      "cost": 3.84,
      "city": "miami",
      "date_str": "2026-03-14",
      "forecast_temp": 81,
      "low": 76,
      "high": 77,
      "opened_at": "2026-03-13T14:00:34.766903"
    },
    "1566221": {
      "strategy": "S2_lottery",
      "question": "Will the highest temperature in Miami be between 86-87\u00b0F on March 14?",
      "outcome": "Yes",
      "entry_price": 0.015,
      "shares": 173.3,
      "cost": 2.6,
      "city": "miami",
      "date_str": "2026-03-14",
      "forecast_temp": 81,
      "low": 86,
      "high": 87,
      "opened_at": "2026-03-13T14:00:34.766917"
    },
    "1574991": {
      "strategy": "S2_lottery",
      "question": "Will the highest temperature in Miami be 75\u00b0F or below on March 15?",
      "outcome": "Yes",
      "entry_price": 0.0115,
      "shares": 229.49,
      "cost": 2.64,
      "city": "miami",
      "date_str": "2026-03-15",
      "forecast_temp": 81,
      "low": -999,
      "high": 75,
      "opened_at": "2026-03-13T14:00:35.620363"
    },
    "1566202": {
      "strategy": "S2_lottery",
      "question": "Will the highest temperature in Dallas be between 84-85\u00b0F on March 14?",
      "outcome": "Yes",
      "entry_price": 0.0375,
      "shares": 139.83,
      "cost": 5.24,
      "city": "dallas",
      "date_str": "2026-03-14",
      "forecast_temp": 83,
      "low": 84,
      "high": 85,
      "opened_at": "2026-03-13T14:00:39.290648"
    },
    "1566203": {
      "strategy": "S2_lottery",
      "question": "Will the highest temperature in Dallas be between 86-87\u00b0F on March 14?",
      "outcome": "Yes",
      "entry_price": 0.0165,
      "shares": 252.55,
      "cost": 4.17,
      "city": "dallas",
      "date_str": "2026-03-14",
      "forecast_temp": 83,
      "low": 86,
      "high": 87,
      "opened_at": "2026-03-13T14:00:39.290685"
    },
    "1566204": {
      "strategy": "S2_lottery",
      "question": "Will the highest temperature in Dallas be between 88-89\u00b0F on March 14?",
      "outcome": "Yes",
      "entry_price": 0.006,
      "shares": 416.34,
      "cost": 2.5,
      "city": "dallas",
      "date_str": "2026-03-14",
      "forecast_temp": 83,
      "low": 88,
      "high": 89,
      "opened_at": "2026-03-13T14:00:39.290695"
    },
    "1574977": {
      "strategy": "S2_lottery",
      "question": "Will the highest temperature in Dallas be between 90-91\u00b0F on March 15?",
      "outcome": "Yes",
      "entry_price": 0.0115,
      "shares": 166.85,
      "cost": 1.92,
      "city": "dallas",
      "date_str": "2026-03-15",
      "forecast_temp": 85,
      "low": 90,
      "high": 91,
      "opened_at": "2026-03-13T14:00:40.156445"
    },
    "1566181": {
      "strategy": "S2_lottery",
      "question": "Will the highest temperature in Seattle be between 40-41\u00b0F on March 14?",
      "outcome": "Yes",
      "entry_price": 0.0355,
      "shares": 56.74,
      "cost": 2.01,
      "city": "seattle",
      "date_str": "2026-03-14",
      "forecast_temp": 45,
      "low": 40,
      "high": 41,
      "opened_at": "2026-03-13T14:00:43.904552"
    },
    "1566208": {
      "strategy": "S2_lottery",
      "question": "Will the highest temperature in Atlanta be between 68-69\u00b0F on March 14?",
      "outcome": "Yes",
      "entry_price": 0.0025,
      "shares": 548.34,
      "cost": 1.37,
      "city": "atlanta",
      "date_str": "2026-03-14",
      "forecast_temp": 75,
      "low": 68,
      "high": 69,
      "opened_at": "2026-03-13T14:00:49.736865"
    },
    "1566209": {
      "strategy": "S2_lottery",
      "question": "Will the highest temperature in Atlanta be between 70-71\u00b0F on March 14?",
      "outcome": "Yes",
      "entry_price": 0.0265,
      "shares": 81.78,
      "cost": 2.17,
      "city": "atlanta",
      "date_str": "2026-03-14",
      "forecast_temp": 75,
      "low": 70,
      "high": 71,
      "opened_at": "2026-03-13T14:00:49.736893"
    },
    "1566214": {
      "strategy": "S2_lottery",
      "question": "Will the highest temperature in Atlanta be 80\u00b0F or higher on March 14?",
      "outcome": "Yes",
      "entry_price": 0.0385,
      "shares": 61.24,
      "cost": 2.36,
      "city": "atlanta",
      "date_str": "2026-03-14",
      "forecast_temp": 75,
      "low": 80,
      "high": 999,
      "opened_at": "2026-03-13T18:32:54.666460"
    },
    "1575006": {
      "strategy": "S2_lottery",
      "question": "Will the highest temperature in Chicago be between 64-65\u00b0F on March 15?",
      "outcome": "Yes",
      "entry_price": 0.035,
      "shares": 89.15,
      "cost": 3.12,
      "city": "chicago",
      "date_str": "2026-03-15",
      "forecast_temp": 62,
      "low": 64,
      "high": 65,
      "opened_at": "2026-03-13T19:27:37.075552"
    },
    "1575007": {
      "strategy": "S2_lottery",
      "question": "Will the highest temperature in Chicago be between 66-67\u00b0F on March 15?",
      "outcome": "Yes",
      "entry_price": 0.0135,
      "shares": 163.72,
      "cost": 2.21,
      "city": "chicago",
      "date_str": "2026-03-15",
      "forecast_temp": 62,
      "low": 66,
      "high": 67,
      "opened_at": "2026-03-13T19:27:37.075571"
    },
    "1575008": {
      "strategy": "S2_lottery",
      "question": "Will the highest temperature in Chicago be 68\u00b0F or higher on March 15?",
      "outcome": "Yes",
      "entry_price": 0.0065,
      "shares": 284.27,
      "cost": 1.85,
      "city": "chicago",
      "date_str": "2026-03-15",
      "forecast_temp": 62,
      "low": 68,
      "high": 999,
      "opened_at": "2026-03-13T19:27:37.075584"
    },
    "1566222": {
      "strategy": "S2_lottery",
      "question": "Will the highest temperature in Miami be between 88-89\u00b0F on March 14?",
      "outcome": "Yes",
      "entry_price": 0.004,
      "shares": 250.91,
      "cost": 1.0,
      "city": "miami",
      "date_str": "2026-03-14",
      "forecast_temp": 82,
      "low": 88,
      "high": 89,
      "opened_at": "2026-03-13T19:27:37.483221"
    },
    "1574976": {
      "strategy": "S1_layered_no",
      "question": "Will the highest temperature in Dallas be between 88-89\u00b0F on March 15?",
      "outcome": "No",
      "entry_price": 0.92,
      "shares": 43.43,
      "cost": 39.95,
      "city": "dallas",
      "date_str": "2026-03-15",
      "forecast_temp": 82,
      "low": 88,
      "high": 89,
      "opened_at": "2026-03-13T19:27:38.143323"
    },
    "1577582": {
      "strategy": "S2_lottery",
      "question": "Will the highest temperature in Dallas be between 52-53\u00b0F on March 16?",
      "outcome": "Yes",
      "entry_price": 0.0155,
      "effective_entry_price": 0.015505,
      "shares": 214.77,
      "cost": 3.33,
      "city": "dallas",
      "date_str": "2026-03-16",
      "forecast_temp": 54,
      "low": 52,
      "high": 53,
      "opened_at": "2026-03-13T19:55:07.526454"
    },
    "1577581": {
      "strategy": "S2_lottery",
      "question": "Will the highest temperature in Dallas be between 50-51\u00b0F on March 16?",
      "outcome": "Yes",
      "entry_price": 0.0155,
      "effective_entry_price": 0.015505,
      "shares": 152.95,
      "cost": 2.37,
      "city": "dallas",
      "date_str": "2026-03-16",
      "forecast_temp": 54,
      "low": 50,
      "high": 51,
      "opened_at": "2026-03-13T19:55:07.526476"
    },
    "1566186": {
      "strategy": "S2_lottery",
      "question": "Will the highest temperature in Seattle be between 50-51\u00b0F on March 14?",
      "outcome": "Yes",
      "entry_price": 0.028,
      "effective_entry_price": 0.028015,
      "shares": 35.69,
      "cost": 1.0,
      "city": "seattle",
      "date_str": "2026-03-14",
      "forecast_temp": 45,
      "low": 50,
      "high": 51,
      "opened_at": "2026-03-13T20:27:09.090783"
    },
    "1577560": {
      "strategy": "S1_layered_no",
      "question": "Will the highest temperature in Seattle be between 46-47\u00b0F on March 16?",
      "outcome": "No",
      "entry_price": 0.87,
      "effective_entry_price": 0.871968,
      "shares": 36.66,
      "cost": 31.96,
      "city": "seattle",
      "date_str": "2026-03-16",
      "forecast_temp": 54,
      "low": 46,
      "high": 47,
      "opened_at": "2026-03-13T20:27:09.241576"
    },
    "1577616": {
      "strategy": "S3_high_conviction",
      "question": "Will the highest temperature in Chicago be between 22-23\u00b0F on March 16?",
      "outcome": "No",
      "entry_price": 0.985,
      "effective_entry_price": 0.985291,
      "shares": 101.51,
      "cost": 100.02,
      "city": "chicago",
      "date_str": "2026-03-16",
      "forecast_temp": 46,
      "low": 22,
      "high": 23,
      "opened_at": "2026-03-13T21:00:23.563535"
    },
    "1574981": {
      "strategy": "S3_high_conviction",
      "question": "Will the highest temperature in Dallas be 98\u00b0F or higher on March 15?",
      "outcome": "No",
      "entry_price": 0.997,
      "effective_entry_price": 0.99706,
      "shares": 100.31,
      "cost": 100.02,
      "city": "dallas",
      "date_str": "2026-03-15",
      "forecast_temp": 82,
      "low": 98,
      "high": 999,
      "opened_at": "2026-03-13T21:00:24.375197"
    }
  },
  "trades": [
    {
      "type": "entry",
      "strategy": "S2_lottery",
      "question": "Will the highest temperature in New York City be between 54-55\u00b0F on March 14?",
      "outcome": "Yes",
      "entry_price": 0.0345,
      "size": 5.24,
      "opened_at": "2026-03-13T14:00:24.926719"
    },
    {
      "type": "entry",
      "strategy": "S2_lottery",
      "question": "Will the highest temperature in New York City be between 56-57\u00b0F on March 14?",
      "outcome": "Yes",
      "entry_price": 0.018,
      "size": 3.07,
      "opened_at": "2026-03-13T14:00:24.926738"
    },
    {
      "type": "entry",
      "strategy": "S2_lottery",
      "question": "Will the highest temperature in Chicago be between 44-45\u00b0F on March 14?",
      "outcome": "Yes",
      "entry_price": 0.0315,
      "size": 4.93,
      "opened_at": "2026-03-13T14:00:30.540480"
    },
    {
      "type": "entry",
      "strategy": "S2_lottery",
      "question": "Will the highest temperature in Chicago be 46\u00b0F or higher on March 14?",
      "outcome": "Yes",
      "entry_price": 0.0055,
      "size": 5.75,
      "opened_at": "2026-03-13T14:00:30.540501"
    },
    {
      "type": "entry",
      "strategy": "S2_lottery",
      "question": "Will the highest temperature in Miami be 75\u00b0F or below on March 14?",
      "outcome": "Yes",
      "entry_price": 0.007,
      "size": 3.16,
      "opened_at": "2026-03-13T14:00:34.766885"
    },
    {
      "type": "entry",
      "strategy": "S2_lottery",
      "question": "Will the highest temperature in Miami be between 76-77\u00b0F on March 14?",
      "outcome": "Yes",
      "entry_price": 0.0125,
      "size": 3.84,
      "opened_at": "2026-03-13T14:00:34.766907"
    },
    {
      "type": "entry",
      "strategy": "S2_lottery",
      "question": "Will the highest temperature in Miami be between 86-87\u00b0F on March 14?",
      "outcome": "Yes",
      "entry_price": 0.015,
      "size": 2.6,
      "opened_at": "2026-03-13T14:00:34.766919"
    },
    {
      "type": "entry",
      "strategy": "S2_lottery",
      "question": "Will the highest temperature in Miami be 75\u00b0F or below on March 15?",
      "outcome": "Yes",
      "entry_price": 0.0115,
      "size": 2.64,
      "opened_at": "2026-03-13T14:00:35.620377"
    },
    {
      "type": "entry",
      "strategy": "S2_lottery",
      "question": "Will the highest temperature in Dallas be between 84-85\u00b0F on March 14?",
      "outcome": "Yes",
      "entry_price": 0.0375,
      "size": 5.24,
      "opened_at": "2026-03-13T14:00:39.290666"
    },
    {
      "type": "entry",
      "strategy": "S2_lottery",
      "question": "Will the highest temperature in Dallas be between 86-87\u00b0F on March 14?",
      "outcome": "Yes",
      "entry_price": 0.0165,
      "size": 4.17,
      "opened_at": "2026-03-13T14:00:39.290687"
    },
    {
      "type": "entry",
      "strategy": "S2_lottery",
      "question": "Will the highest temperature in Dallas be between 88-89\u00b0F on March 14?",
      "outcome": "Yes",
      "entry_price": 0.006,
      "size": 2.5,
      "opened_at": "2026-03-13T14:00:39.290698"
    },
    {
      "type": "entry",
      "strategy": "S2_lottery",
      "question": "Will the highest temperature in Dallas be between 90-91\u00b0F on March 15?",
      "outcome": "Yes",
      "entry_price": 0.0115,
      "size": 1.92,
      "opened_at": "2026-03-13T14:00:40.156458"
    },
    {
      "type": "entry",
      "strategy": "S2_lottery",
      "question": "Will the highest temperature in Seattle be between 40-41\u00b0F on March 14?",
      "outcome": "Yes",
      "entry_price": 0.0355,
      "size": 2.01,
      "opened_at": "2026-03-13T14:00:43.904563"
    },
    {
      "type": "entry",
      "strategy": "S2_lottery",
      "question": "Will the highest temperature in Atlanta be between 68-69\u00b0F on March 14?",
      "outcome": "Yes",
      "entry_price": 0.0025,
      "size": 1.37,
      "opened_at": "2026-03-13T14:00:49.736878"
    },
    {
      "type": "entry",
      "strategy": "S2_lottery",
      "question": "Will the highest temperature in Atlanta be between 70-71\u00b0F on March 14?",
      "outcome": "Yes",
      "entry_price": 0.0265,
      "size": 2.17,
      "opened_at": "2026-03-13T14:00:49.736896"
    },
    {
      "type": "entry",
      "strategy": "S1_layered_no",
      "question": "Will the highest temperature in Atlanta be between 68-69\u00b0F on March 15?",
      "outcome": "No",
      "entry_price": 0.965,
      "size": 40.0,
      "opened_at": "2026-03-13T14:00:50.450308"
    },
    {
      "type": "entry",
      "strategy": "S3_high_conviction",
      "question": "Will the highest temperature in Atlanta be 57\u00b0F or below on March 15?",
      "outcome": "No",
      "entry_price": 0.9975,
      "size": 200.0,
      "opened_at": "2026-03-13T14:00:50.450330"
    },
    {
      "type": "exit",
      "strategy": "S1_layered_no",
      "question": "Will the highest temperature in Atlanta be between 68-69\u00b0F on March 15?",
      "outcome": "No",
      "entry_price": 0.965,
      "exit_price": 0.964,
      "pnl": -0.04,
      "closed_at": "2026-03-13T18:32:34.774833"
    },
    {
      "type": "exit",
      "strategy": "S3_high_conviction",
      "question": "Will the highest temperature in Atlanta be 57\u00b0F or below on March 15?",
      "outcome": "No",
      "entry_price": 0.9975,
      "exit_price": 0.9975,
      "pnl": 0.0,
      "closed_at": "2026-03-13T18:32:35.055548"
    },
    {
      "type": "entry",
      "strategy": "S2_lottery",
      "question": "Will the highest temperature in Atlanta be 80\u00b0F or higher on March 14?",
      "outcome": "Yes",
      "entry_price": 0.0385,
      "size": 2.36,
      "opened_at": "2026-03-13T18:32:54.666466"
    },
    {
      "type": "entry",
      "strategy": "S1_layered_no",
      "question": "Will the highest temperature in Atlanta be between 68-69\u00b0F on March 15?",
      "outcome": "No",
      "entry_price": 0.964,
      "size": 39.99,
      "opened_at": "2026-03-13T18:32:54.766398"
    },
    {
      "type": "entry",
      "strategy": "S3_high_conviction",
      "question": "Will the highest temperature in Atlanta be 57\u00b0F or below on March 15?",
      "outcome": "No",
      "entry_price": 0.9975,
      "size": 200.0,
      "opened_at": "2026-03-13T18:32:54.766434"
    },
    {
      "type": "exit",
      "strategy": "S1_layered_no",
      "question": "Will the highest temperature in Atlanta be between 68-69\u00b0F on March 15?",
      "outcome": "No",
      "entry_price": 0.964,
      "exit_price": 0.9595,
      "pnl": -0.19,
      "closed_at": "2026-03-13T19:27:35.338847"
    },
    {
      "type": "exit",
      "strategy": "S3_high_conviction",
      "question": "Will the highest temperature in Atlanta be 57\u00b0F or below on March 15?",
      "outcome": "No",
      "entry_price": 0.9975,
      "exit_price": 0.9975,
      "pnl": 0.0,
      "closed_at": "2026-03-13T19:27:35.571963"
    },
    {
      "type": "entry",
      "strategy": "S2_lottery",
      "question": "Will the highest temperature in Chicago be between 64-65\u00b0F on March 15?",
      "outcome": "Yes",
      "entry_price": 0.035,
      "size": 3.12,
      "opened_at": "2026-03-13T19:27:37.075558"
    },
    {
      "type": "entry",
      "strategy": "S2_lottery",
      "question": "Will the highest temperature in Chicago be between 66-67\u00b0F on March 15?",
      "outcome": "Yes",
      "entry_price": 0.0135,
      "size": 2.21,
      "opened_at": "2026-03-13T19:27:37.075574"
    },
    {
      "type": "entry",
      "strategy": "S2_lottery",
      "question": "Will the highest temperature in Chicago be 68\u00b0F or higher on March 15?",
      "outcome": "Yes",
      "entry_price": 0.0065,
      "size": 1.85,
      "opened_at": "2026-03-13T19:27:37.075586"
    },
    {
      "type": "entry",
      "strategy": "S2_lottery",
      "question": "Will the highest temperature in Miami be between 88-89\u00b0F on March 14?",
      "outcome": "Yes",
      "entry_price": 0.004,
      "size": 1.0,
      "opened_at": "2026-03-13T19:27:37.483226"
    },
    {
      "type": "entry",
      "strategy": "S1_layered_no",
      "question": "Will the highest temperature in Dallas be between 88-89\u00b0F on March 15?",
      "outcome": "No",
      "entry_price": 0.92,
      "size": 39.95,
      "opened_at": "2026-03-13T19:27:38.143328"
    },
    {
      "type": "entry",
      "strategy": "S3_high_conviction",
      "question": "Will the highest temperature in Dallas be 98\u00b0F or higher on March 15?",
      "outcome": "No",
      "entry_price": 0.9965,
      "size": 200.0,
      "opened_at": "2026-03-13T19:27:38.143344"
    },
    {
      "type": "exit",
      "strategy": "S3_high_conviction",
      "question": "Will the highest temperature in Dallas be 98\u00b0F or higher on March 15?",
      "outcome": "No",
      "entry_price": 0.9965,
      "exit_price": 0.997,
      "pnl": 0.1,
      "closed_at": "2026-03-13T19:55:04.702127"
    },
    {
      "type": "entry",
      "strategy": "S3_high_conviction",
      "question": "Will the highest temperature in Dallas be 98\u00b0F or higher on March 15?",
      "outcome": "No",
      "entry_price": 0.997,
      "size": 200.1,
      "opened_at": "2026-03-13T19:55:07.458308"
    },
    {
      "type": "entry",
      "strategy": "S2_lottery",
      "question": "Will the highest temperature in Dallas be between 52-53\u00b0F on March 16?",
      "outcome": "Yes",
      "entry_price": 0.0155,
      "size": 3.33,
      "opened_at": "2026-03-13T19:55:07.526461"
    },
    {
      "type": "entry",
      "strategy": "S2_lottery",
      "question": "Will the highest temperature in Dallas be between 50-51\u00b0F on March 16?",
      "outcome": "Yes",
      "entry_price": 0.0155,
      "size": 2.37,
      "opened_at": "2026-03-13T19:55:07.526478"
    },
    {
      "type": "exit",
      "strategy": "S3_high_conviction",
      "question": "Will the highest temperature in Dallas be 98\u00b0F or higher on March 15?",
      "outcome": "No",
      "entry_price": 0.997,
      "exit_price": 0.997,
      "pnl": -0.01,
      "closed_at": "2026-03-13T19:57:05.056436"
    },
    {
      "type": "entry",
      "strategy": "S3_high_conviction",
      "question": "Will the highest temperature in Dallas be 98\u00b0F or higher on March 15?",
      "outcome": "No",
      "entry_price": 0.997,
      "size": 200.09,
      "opened_at": "2026-03-13T19:57:07.272821"
    },
    {
      "type": "exit",
      "strategy": "S3_high_conviction",
      "question": "Will the highest temperature in Dallas be 98\u00b0F or higher on March 15?",
      "outcome": "No",
      "entry_price": 0.997,
      "exit_price": 0.997,
      "pnl": -0.01,
      "closed_at": "2026-03-13T20:27:06.605580"
    },
    {
      "type": "entry",
      "strategy": "S3_high_conviction",
      "question": "Will the highest temperature in Chicago be between 22-23\u00b0F on March 16?",
      "outcome": "No",
      "entry_price": 0.985,
      "size": 100.04,
      "opened_at": "2026-03-13T20:27:07.733046"
    },
    {
      "type": "entry",
      "strategy": "S3_high_conviction",
      "question": "Will the highest temperature in Dallas be 98\u00b0F or higher on March 15?",
      "outcome": "No",
      "entry_price": 0.997,
      "size": 100.04,
      "opened_at": "2026-03-13T20:27:08.650389"
    },
    {
      "type": "entry",
      "strategy": "S2_lottery",
      "question": "Will the highest temperature in Seattle be between 50-51\u00b0F on March 14?",
      "outcome": "Yes",
      "entry_price": 0.028,
      "size": 1.0,
      "opened_at": "2026-03-13T20:27:09.090789"
    },
    {
      "type": "entry",
      "strategy": "S1_layered_no",
      "question": "Will the highest temperature in Seattle be between 46-47\u00b0F on March 16?",
      "outcome": "No",
      "entry_price": 0.87,
      "size": 31.96,
      "opened_at": "2026-03-13T20:27:09.241583"
    },
    {
      "type": "exit",
      "strategy": "S3_high_conviction",
      "question": "Will the highest temperature in Chicago be between 22-23\u00b0F on March 16?",
      "outcome": "No",
      "entry_price": 0.985,
      "exit_price": 0.985,
      "pnl": -0.03,
      "closed_at": "2026-03-13T21:00:21.549286"
    },
    {
      "type": "exit",
      "strategy": "S3_high_conviction",
      "question": "Will the highest temperature in Dallas be 98\u00b0F or higher on March 15?",
      "outcome": "No",
      "entry_price": 0.997,
      "exit_price": 0.997,
      "pnl": -0.01,
      "closed_at": "2026-03-13T21:00:21.765468"
    },
    {
      "type": "entry",
      "strategy": "S3_high_conviction",
      "question": "Will the highest temperature in Chicago be between 22-23\u00b0F on March 16?",
      "outcome": "No",
      "entry_price": 0.985,
      "size": 100.02,
      "opened_at": "2026-03-13T21:00:23.563542"
    },
    {
      "type": "entry",
      "strategy": "S3_high_conviction",
      "question": "Will the highest temperature in Dallas be 98\u00b0F or higher on March 15?",
      "outcome": "No",
      "entry_price": 0.997,
      "size": 100.02,
      "opened_at": "2026-03-13T21:00:24.375202"
    }
  ],
  "total_trades": 36,
  "wins": 1,
  "losses": 8,
  "peak_balance": 500.0
}